tivelo/__init__.py
tivelo/main.py
tivelo/direction/__init__.py
tivelo/direction/correct.py
tivelo/direction/linear_tree.py
tivelo/direction/model.py
tivelo/path/__init__.py
tivelo/path/main_path.py
tivelo/path/process.py
tivelo/path/prune.py
tivelo/path/start_node.py
tivelo/plotting/__init__.py
tivelo/plotting/velo_vec_plot.py
tivelo/utils/__init__.py
tivelo/utils/metrics.py
tivelo/utils/velocity_genes.py
tivelo/velocity/DTI.py
tivelo/velocity/__init__.py
tivelo/velocity/model.py
tivelo/velocity/model_rate.py
tivelo-0.1.4.dist-info/licenses/LICENSE
tivelo-0.1.4.dist-info/METADATA
tivelo-0.1.4.dist-info/WHEEL
tivelo-0.1.4.dist-info/top_level.txt
tivelo-0.1.4.dist-info/RECORD
